README.md
setup.cfg
setup.py
iot_services_sdk/__init__.py
iot_services_sdk/about.py
iot_services_sdk/capability.py
iot_services_sdk/device.py
iot_services_sdk/gateway.py
iot_services_sdk/iot_service.py
iot_services_sdk/mqtt_client.py
iot_services_sdk/protocol.py
iot_services_sdk/response.py
iot_services_sdk/rest_client.py
iot_services_sdk/sensor.py
iot_services_sdk/sensor_type.py
iot_services_sdk/session.py
iot_services_sdk/tenant.py
iot_services_sdk/tenant_iot_service.py
iot_services_sdk/user.py
iot_services_sdk/utils.py
iot_services_sdk/vendor.py
iot_services_sdk.egg-info/PKG-INFO
iot_services_sdk.egg-info/SOURCES.txt
iot_services_sdk.egg-info/dependency_links.txt
iot_services_sdk.egg-info/requires.txt
iot_services_sdk.egg-info/top_level.txt