Metadata-Version: 2.1
Name: iot-services-sdk
Version: 2.0.0
Summary: SDK for SAP IoT Services on Cloud Foundry. Wraps all Device Management APIs as well as both Cloud Gateways.
Home-page: https://github.com/SAP/iot-services-sdk
Author: Philipp Steinrötter
Author-email: philipp.steinroetter@sap.com
License: SAP Sample Code License
Download-URL: https://github.com/SAP/iot-services-sdk/archive/1.0.tar.gz
Keywords: SAP IoT Services CF SDK MQTT REST Device Management Internet of Things
Platform: UNKNOWN
Classifier: Development Status :: 5 - Production/Stable
Classifier: Intended Audience :: Developers
Classifier: Programming Language :: Python :: 3
Classifier: Programming Language :: Python :: 3.4
Classifier: Programming Language :: Python :: 3.5
Classifier: Programming Language :: Python :: 3.6
Classifier: Programming Language :: Python :: 3.7
Requires-Python: >=3
